{
  "required": true,
  "minVersion": "0.8",
  "package": "me.wurgo.pogworld.mixin",
  "compatibilityLevel": "JAVA_8",
  "client": [
    "access.EndCityFeatureAccess",
    "access.EndCityGeneratorAccess",
    "generation.ShipwreckGeneratorMixin",
    "generation.BlockAgeStructureProcessorMixin",
    "generation.SpikeMixin",
    "generation.ServerWorldMixin",
    "generation.EndCityFeatureStartMixin",
    "generation.VillageFeatureStartMixin",
    "generation.StructuresConfigMixin",
    "generation.StrongholdGeneratorMixin",
    "generation.PortalRoomMixin",
    "generation.StrongholdConfigMixin",
    "generation.StrongholdFeatureMixin",
    "generation.ChunkGeneratorMixin",
    "DebugHudMixin"
  ],
  "injectors": {
    "defaultRequire": 1
  }
}
